synthtiger/__init__.py
synthtiger/__main__.py
synthtiger/_version.py
synthtiger/gen.py
synthtiger/main.py
synthtiger/components/__init__.py
synthtiger/components/component.py
synthtiger/components/color/__init__.py
synthtiger/components/color/color_map.py
synthtiger/components/color/gray.py
synthtiger/components/color/gray_map.py
synthtiger/components/color/opacity.py
synthtiger/components/color/rgb.py
synthtiger/components/color/rgb_map.py
synthtiger/components/corpus/__init__.py
synthtiger/components/corpus/base_corpus.py
synthtiger/components/corpus/char_augmentable_corpus.py
synthtiger/components/corpus/length_augmentable_corpus.py
synthtiger/components/font/__init__.py
synthtiger/components/font/base_font.py
synthtiger/components/image_effect/__init__.py
synthtiger/components/image_effect/additive_gaussian_noise.py
synthtiger/components/image_effect/brightness.py
synthtiger/components/image_effect/coarse_dropout.py
synthtiger/components/image_effect/contrast.py
synthtiger/components/image_effect/dilate.py
synthtiger/components/image_effect/elastic_distortion.py
synthtiger/components/image_effect/erode.py
synthtiger/components/image_effect/grayscale.py
synthtiger/components/image_effect/gussian_blur.py
synthtiger/components/image_effect/image_rotate.py
synthtiger/components/image_effect/jpeg_compression.py
synthtiger/components/image_effect/median_blur.py
synthtiger/components/image_effect/motion_blur.py
synthtiger/components/image_effect/resample.py
synthtiger/components/image_effect/shadow.py
synthtiger/components/layout/__init__.py
synthtiger/components/layout/curve_layout.py
synthtiger/components/layout/flow_layout.py
synthtiger/components/text_effect/__init__.py
synthtiger/components/text_effect/text_border.py
synthtiger/components/text_effect/text_extrusion.py
synthtiger/components/text_effect/text_shadow.py
synthtiger/components/text_effect/text_sprinkle.py
synthtiger/components/texture/__init__.py
synthtiger/components/texture/base_texture.py
synthtiger-1.2.1.dist-info/LICENSE
synthtiger-1.2.1.dist-info/METADATA
synthtiger-1.2.1.dist-info/NOTICE
synthtiger-1.2.1.dist-info/WHEEL
synthtiger-1.2.1.dist-info/entry_points.txt
synthtiger-1.2.1.dist-info/top_level.txt
synthtiger-1.2.1.dist-info/RECORD
