Metadata-Version: 2.1
Name: synthtiger
Version: 1.2.1
Summary: Synthetic text image generator for OCR model
Home-page: https://github.com/clovaai/synthtiger
Author: Moonbin Yim, Yoonsik Kim, Han-Cheol Cho, Sungrae Park
License: MIT
Classifier: Development Status :: 4 - Beta
Classifier: Intended Audience :: Developers
Classifier: Intended Audience :: Information Technology
Classifier: Intended Audience :: Science/Research
Classifier: License :: OSI Approved :: MIT License
Classifier: Operating System :: OS Independent
Classifier: Programming Language :: Python
Classifier: Programming Language :: Python :: 3
Classifier: Programming Language :: Python :: 3.6
Classifier: Programming Language :: Python :: 3.7
Classifier: Programming Language :: Python :: 3.8
Classifier: Programming Language :: Python :: 3.9
Classifier: Programming Language :: Python :: 3.10
Classifier: Topic :: Scientific/Engineering :: Artificial Intelligence
Classifier: Topic :: Scientific/Engineering :: Image Processing
Classifier: Topic :: Scientific/Engineering :: Image Recognition
Classifier: Topic :: Software Development :: Libraries
Classifier: Topic :: Software Development :: Libraries :: Python Modules
Requires-Python: >=3.6
License-File: LICENSE
License-File: NOTICE
Requires-Dist: arabic-reshaper
Requires-Dist: blend-modes
Requires-Dist: fonttools
Requires-Dist: imgaug
Requires-Dist: numpy
Requires-Dist: opencv-python
Requires-Dist: pillow (>=8.2.0)
Requires-Dist: pygame
Requires-Dist: python-bidi
Requires-Dist: pytweening
Requires-Dist: pyyaml
Requires-Dist: regex
Requires-Dist: scipy
